Metadata-Version: 1.1
Name: twitterEye
Version: 1.0.0
Summary: Analyze and visualize how public is reacting to a certain topic on Twitter
Home-page: UNKNOWN
Author: Hinan Bilal
Author-email: hinanbilalshah@gmail.com
License: MIT
Keywords: twitter sentimentanalysis visualization
Platform: UNKNOWN
Classifier: Development Status :: 5 - Production/Stable
Classifier: Intended Audience :: Education
Classifier: Operating System :: Microsoft :: Windows :: Windows 10
Classifier: License :: OSI Approved :: MIT License
Classifier: Programming Language :: Python :: 3
